cachy/__init__.py
cachy/_modidx.py
cachy/core.py
pycachy-0.0.4.dist-info/licenses/LICENSE
pycachy-0.0.4.dist-info/METADATA
pycachy-0.0.4.dist-info/WHEEL
pycachy-0.0.4.dist-info/entry_points.txt
pycachy-0.0.4.dist-info/top_level.txt
pycachy-0.0.4.dist-info/RECORD
