Metadata-Version: 2.4
Name: pycachy
Version: 0.0.4
Summary: Cache your API calls with a single line of code. No mocks, no fixtures. Just faster, cleaner code.
Home-page: https://github.com/AnswerDotAI/cachy
Author: Tommy
Author-email: tc@answer.ai
License: Apache Software License 2.0
Keywords: nbdev jupyter notebook python
Classifier: Development Status :: 4 - Beta
Classifier: Intended Audience :: Developers
Classifier: Natural Language :: English
Classifier: Programming Language :: Python :: 3.9
Classifier: Programming Language :: Python :: 3.10
Classifier: Programming Language :: Python :: 3.11
Classifier: Programming Language :: Python :: 3.12
Classifier: License :: OSI Approved :: Apache Software License
Requires-Python: >=3.9
License-File: LICENSE
Requires-Dist: fastcore
Requires-Dist: httpx
Provides-Extra: dev
Requires-Dist: openai; extra == "dev"
Requires-Dist: anthropic; extra == "dev"
Requires-Dist: litellm; extra == "dev"
Requires-Dist: nbdev; extra == "dev"
Dynamic: author
Dynamic: author-email
Dynamic: classifier
Dynamic: description
Dynamic: description-content-type
Dynamic: home-page
Dynamic: keywords
Dynamic: license
Dynamic: license-file
Dynamic: provides-extra
Dynamic: requires-dist
Dynamic: requires-python
Dynamic: summary
